apv/__init__.py
apv/apv.py
apv-4.2.2.dist-info/licenses/LICENSE
apv-4.2.2.dist-info/METADATA
apv-4.2.2.dist-info/WHEEL
apv-4.2.2.dist-info/top_level.txt
apv-4.2.2.dist-info/RECORD
