Metadata-Version: 2.4
Name: apv
Version: 4.2.2
Summary: Advanced Python Logging
Home-page: https://github.com/acidvegas/apv
Author: acidvegas
Author-email: acid.vegas@acid.vegas
License: ISC
Project-URL: Bug Tracker, https://github.com/acidvegas/apv/issues
Project-URL: Documentation, https://github.com/acidvegas/apv/wiki
Project-URL: Source Code, https://github.com/acidvegas/apv
Classifier: Programming Language :: Python :: 3
Classifier: License :: OSI Approved :: ISC License (ISCL)
Classifier: Operating System :: OS Independent
License-File: LICENSE
Dynamic: author
Dynamic: author-email
Dynamic: classifier
Dynamic: description
Dynamic: description-content-type
Dynamic: home-page
Dynamic: license
Dynamic: license-file
Dynamic: project-url
Dynamic: summary
